LICENSE
MANIFEST.in
README.md
setup.py
txgossip/__init__.py
txgossip/detector.py
txgossip/gossip.py
txgossip/recipies.py
txgossip/scuttle.py
txgossip/state.py
txgossip.egg-info/PKG-INFO
txgossip.egg-info/SOURCES.txt
txgossip.egg-info/dependency_links.txt
txgossip.egg-info/top_level.txt
txgossip/test/__init__.py
txgossip/test/test_keystore.py
txgossip/test/test_leader.py