Metadata-Version: 1.0
Name: txgossip
Version: 0.1
Summary: simple cluster communication protocol
Home-page: http://github.com/jrydberg/txgossip
Author: Johan Rydberg
Author-email: johan.rydberg@gmail.com
License: UNKNOWN
Platform: UNKNOWN
